lib_dzne_cBASE.py
lib_dzne_cBASE-0.1.0.dist-info/LICENSE
lib_dzne_cBASE-0.1.0.dist-info/METADATA
lib_dzne_cBASE-0.1.0.dist-info/WHEEL
lib_dzne_cBASE-0.1.0.dist-info/top_level.txt
lib_dzne_cBASE-0.1.0.dist-info/RECORD
