Metadata-Version: 2.1
Name: lib-dzne-cBASE
Version: 0.1.0
Summary: Libary for aligning and comparing seqreads. 
Author-email: Johannes Horler <johannes.horler@dzne.de>
License: Copyright © 2022 Johannes Horler
Classifier: License :: OSI Approved :: MIT License
Classifier: Programming Language :: Python
Classifier: Programming Language :: Python :: 3
Requires-Python: >=3.11
License-File: LICENSE
Requires-Dist: lib-dzne-data (>=0.1.2)
Requires-Dist: lib-dzne-seq (>=0.1.1)
